keboola/__init__.py
keboola/skill_registry_mcp/__init__.py
keboola/skill_registry_mcp/__main__.py
keboola/skill_registry_mcp/cli.py
keboola/skill_registry_mcp/client.py
keboola/skill_registry_mcp/config.py
keboola/skill_registry_mcp/mcp.py
keboola/skill_registry_mcp/server.py
keboola/skill_registry_mcp/sr_tools.py
keboola_skill_registry_mcp-0.0.9.dist-info/licenses/LICENSE
keboola_skill_registry_mcp-0.0.9.dist-info/METADATA
keboola_skill_registry_mcp-0.0.9.dist-info/WHEEL
keboola_skill_registry_mcp-0.0.9.dist-info/entry_points.txt
keboola_skill_registry_mcp-0.0.9.dist-info/top_level.txt
keboola_skill_registry_mcp-0.0.9.dist-info/RECORD
